steprate.py
steprate-0.0.0.dist-info/METADATA
steprate-0.0.0.dist-info/WHEEL
steprate-0.0.0.dist-info/top_level.txt
steprate-0.0.0.dist-info/RECORD
