Metadata-Version: 2.1
Name: steprate
Version: 0.0.0
Summary: 计算阶梯扣率或阶梯分成的一组方法
Keywords: 阶梯扣率,阶梯分成,扣除,阶梯,扣率,分成,step,rate
